kwplot/__init__.py
kwplot/__main__.py
kwplot/__main__.pyi
kwplot/auto_backends.py
kwplot/auto_backends.pyi
kwplot/draw_conv.py
kwplot/draw_conv.pyi
kwplot/managers.py
kwplot/mpl_3d.py
kwplot/mpl_3d.pyi
kwplot/mpl_color.py
kwplot/mpl_color.pyi
kwplot/mpl_core.py
kwplot/mpl_core.pyi
kwplot/mpl_draw.py
kwplot/mpl_draw.pyi
kwplot/mpl_make.py
kwplot/mpl_make.pyi
kwplot/mpl_multiplot.py
kwplot/mpl_multiplot.pyi
kwplot/mpl_plotnums.py
kwplot/mpl_plotnums.pyi
kwplot/py.typed
kwplot/tables.py
kwplot/util_seaborn.py
kwplot/video_writer.py
kwplot/cli/__init__.py
kwplot/cli/__main__.py
kwplot/cli/__main__.pyi
kwplot/cli/adjust_gui.py
kwplot/cli/adjust_gui.pyi
kwplot/cli/gifify.py
kwplot/cli/gifify.pyi
kwplot/cli/main.py
kwplot/cli/main.pyi
kwplot-0.5.4.dist-info/licenses/LICENSE
kwplot-0.5.4.dist-info/METADATA
kwplot-0.5.4.dist-info/WHEEL
kwplot-0.5.4.dist-info/top_level.txt
kwplot-0.5.4.dist-info/RECORD
